dictionary/__init__.py
dictionary/dictionary.py
Dictionary_HW1-2.0.1.dist-info/METADATA
Dictionary_HW1-2.0.1.dist-info/WHEEL
Dictionary_HW1-2.0.1.dist-info/top_level.txt
Dictionary_HW1-2.0.1.dist-info/RECORD
