Metadata-Version: 2.1
Name: Dictionary-HW1
Version: 2.0.1
Summary: UNKNOWN
Author: Idil Yilmaz
License: UNKNOWN
Platform: UNKNOWN
Requires-Python: >=3.8
Requires-Dist: requests (>=2.23.0)
